CHANGELOG.rst
LICENSE.txt
MANIFEST.in
README.rst
TODO.txt
VERSION.txt
setup.cfg
setup.py
morph/__init__.py
morph/test.py
morph.egg-info/PKG-INFO
morph.egg-info/SOURCES.txt
morph.egg-info/dependency_links.txt
morph.egg-info/top_level.txt
morph.egg-info/zip-safe