Metadata-Version: 1.1
Name: morph
Version: 0.1.2
Summary: A collection of routines to help identify and morph objects.
Home-page: http://github.com/metagriffin/morph
Author: metagriffin
Author-email: mg.pypi@uberdev.org
License: GPLv3+
Keywords: morph string list tuple dict flatten unflatten tolist tobool pick omit
Platform: any
Classifier: Development Status :: 4 - Beta
Classifier: Intended Audience :: Developers
Classifier: Operating System :: OS Independent
Classifier: Programming Language :: Python
Classifier: Topic :: Software Development
Classifier: Topic :: Software Development :: Libraries :: Python Modules
Classifier: Topic :: Utilities
Classifier: License :: OSI Approved :: GNU General Public License v3 or later (GPLv3+)
